nornir/__init__.py
nornir/core/__init__.py
nornir/core/configuration.py
nornir/core/exceptions.py
nornir/core/inventory.py
nornir/core/task.py
nornir/core/helpers/__init__.py
nornir/core/helpers/jinja_helper.py
nornir/plugins/__init__.py
nornir/plugins/functions/__init__.py
nornir/plugins/functions/inv/__init__.py
nornir/plugins/functions/inv/helper.py
nornir/plugins/functions/text/__init__.py
nornir/plugins/functions/text/filter.py
nornir/plugins/functions/text/ptable.py
nornir/plugins/inventory/__init__.py
nornir/plugins/inventory/ansible.py
nornir/plugins/inventory/nsot.py
nornir/plugins/inventory/simple.py
nornir/plugins/tasks/__init__.py
nornir/plugins/tasks/apis/__init__.py
nornir/plugins/tasks/apis/http_method.py
nornir/plugins/tasks/apis/gw/__init__.py
nornir/plugins/tasks/apis/gw/gw_request.py
nornir/plugins/tasks/apis/gw/helper.py
nornir/plugins/tasks/commands/__init__.py
nornir/plugins/tasks/commands/command.py
nornir/plugins/tasks/commands/remote_command.py
nornir/plugins/tasks/connections/__init__.py
nornir/plugins/tasks/connections/napalm_connection.py
nornir/plugins/tasks/connections/netmiko_connection.py
nornir/plugins/tasks/connections/paramiko_connection.py
nornir/plugins/tasks/data/__init__.py
nornir/plugins/tasks/data/load_json.py
nornir/plugins/tasks/data/load_yaml.py
nornir/plugins/tasks/files/__init__.py
nornir/plugins/tasks/files/sftp.py
nornir/plugins/tasks/files/write_file.py
nornir/plugins/tasks/networking/__init__.py
nornir/plugins/tasks/networking/napalm_cli.py
nornir/plugins/tasks/networking/napalm_configure.py
nornir/plugins/tasks/networking/napalm_get.py
nornir/plugins/tasks/networking/napalm_validate.py
nornir/plugins/tasks/networking/netmiko_file_transfer.py
nornir/plugins/tasks/networking/netmiko_send_command.py
nornir/plugins/tasks/networking/netmiko_send_config.py
nornir/plugins/tasks/networking/tcp_ping.py
nornir/plugins/tasks/text/__init__.py
nornir_bics-0.0.1.dist-info/METADATA
nornir_bics-0.0.1.dist-info/RECORD
nornir_bics-0.0.1.dist-info/WHEEL
nornir_bics-0.0.1.dist-info/top_level.txt
