Metadata-Version: 2.1
Name: nornir-bics
Version: 0.0.1
Summary: Fork of Nornir with customized plugins
Home-page: https://github.com/nornir-automation/nornir
Author: walter.de.smedt@bics.com
License: Apache License, version 2
Platform: any
Classifier: Development Status :: 4 - Beta
Classifier: Programming Language :: Python :: 3.6
Requires-Dist: colorama
Requires-Dist: pyyaml
Requires-Dist: jinja2
Requires-Dist: napalm (>=2.3.0)
Requires-Dist: netmiko (>=2.1.1)
Requires-Dist: paramiko
Requires-Dist: future
Requires-Dist: requests
Requires-Dist: ruamel.yaml
Requires-Dist: ptable
Requires-Dist: tqdm
